json_to_parquet/__init__.py
json_to_parquet/__main__.py
json_to_parquet/_native.cpython-313-x86_64-linux-gnu.so
json_to_parquet/cli.py
json_to_parquet-0.1.0.dist-info/METADATA
json_to_parquet-0.1.0.dist-info/WHEEL
json_to_parquet-0.1.0.dist-info/entry_points.txt
json_to_parquet-0.1.0.dist-info/RECORD
json_to_parquet-0.1.0.dist-info/licenses/LICENSE
