Metadata-Version: 2.4
Name: json_to_parquet
Version: 0.1.0
Classifier: Programming Language :: Rust
Classifier: Programming Language :: Python :: Implementation :: CPython
Classifier: Programming Language :: Python :: 3.11
Classifier: Programming Language :: Python :: 3.12
Requires-Dist: pytest ; extra == 'dev'
Requires-Dist: pandas ; extra == 'dev'
Requires-Dist: pyarrow ; extra == 'dev'
Requires-Dist: maturin ; extra == 'dev'
Provides-Extra: dev
License-File: LICENSE
Summary: Memory-efficient JSON to Parquet converter
Requires-Python: >=3.11
